{
  "transhis": [
    {
      "time": "15:00:00",
      "price": 11.58,
      "change": 0,
      "voturnover": 0,
      "vaturnover": 0
    },
    {
      "time": "15:00:00",
      "price": 11.58,
      "change": -0.01,
      "voturnover": 103,
      "vaturnover": 119274
    },
    {
      "time": "14:57:11",
      "price": 11.59,
      "change": 0,
      "voturnover": 0,
      "vaturnover": 0
    },
    {
      "time": "14:57:03",
      "price": 11.59,
      "change": 0,
      "voturnover": 0,
      "vaturnover": 0
    },
    {
      "time": "14:56:38",
      "price": 11.59,
      "change": 0.01,
      "voturnover": 1,
      "vaturnover": 1159
    },
    {
      "time": "14:55:56",
      "price": 11.58,
      "change": -0.01,
      "voturnover": 100,
      "vaturnover": 115800
    },
    {
      "time": "14:55:38",
      "price": 11.59,
      "change": 0,
      "voturnover": 14,
      "vaturnover": 16226
    },
    {
      "time": "14:54:38",
      "price": 11.59,
      "change": 0,
      "voturnover": 9,
      "vaturnover": 10431
    },
    {
      "time": "14:54:26",
      "price": 11.59,
      "change": -0.01,
      "voturnover": 8,
      "vaturnover": 9272
    },
    {
      "time": "14:54:23",
      "price": 11.6,
      "change": 0,
      "voturnover": 50,
      "vaturnover": 58000
    },
    {
      "time": "14:53:44",
      "price": 11.6,
      "change": 0.01,
      "voturnover": 30,
      "vaturnover": 34800
    },
    {
      "time": "14:53:32",
      "price": 11.59,
      "change": 0.01,
      "voturnover": 9,
      "vaturnover": 10431
    },
    {
      "time": "14:52:44",
      "price": 11.58,
      "change": 0,
      "voturnover": 10,
      "vaturnover": 11580
    },
    {
      "time": "14:52:29",
      "price": 11.58,
      "change": 0,
      "voturnover": 21,
      "vaturnover": 24318
    },
    {
      "time": "14:51:29",
      "price": 11.58,
      "change": -0.01,
      "voturnover": 5,
      "vaturnover": 5790
    },
    {
      "time": "14:50:53",
      "price": 11.59,
      "change": -0.01,
      "voturnover": 21,
      "vaturnover": 24339
    },
    {
      "time": "14:50:08",
      "price": 11.6,
      "change": 0,
      "voturnover": 12,
      "vaturnover": 13920
    },
    {
      "time": "14:48:29",
      "price": 11.6,
      "change": 0,
      "voturnover": 0,
      "vaturnover": 0
    },
    {
      "time": "14:47:44",
      "price": 11.6,
      "change": 0,
      "voturnover": 1,
      "vaturnover": 1160
    },
    {
      "time": "14:46:41",
      "price": 11.6,
      "change": 0,
      "voturnover": 77,
      "vaturnover": 89320
    },
    {
      "time": "14:46:05",
      "price": 11.6,
      "change": 0,
      "voturnover": 2,
      "vaturnover": 2320
    },
    {
      "time": "14:46:02",
      "price": 11.6,
      "change": -0.02,
      "voturnover": 2,
      "vaturnover": 2320
    },
    {
      "time": "14:43:32",
      "price": 11.62,
      "change": 0.02,
      "voturnover": 3,
      "vaturnover": 3486
    },
    {
      "time": "14:43:02",
      "price": 11.6,
      "change": -0.02,
      "voturnover": 1,
      "vaturnover": 1160
    },
    {
      "time": "14:42:20",
      "price": 11.62,
      "change": 0.02,
      "voturnover": 3,
      "vaturnover": 3486
    },
    {
      "time": "14:42:05",
      "price": 11.6,
      "change": -0.02,
      "voturnover": 3,
      "vaturnover": 3480
    },
    {
      "time": "14:42:02",
      "price": 11.62,
      "change": 0.01,
      "voturnover": 4,
      "vaturnover": 4648
    },
    {
      "time": "14:41:50",
      "price": 11.61,
      "change": 0,
      "voturnover": 90,
      "vaturnover": 104490
    },
    {
      "time": "14:40:32",
      "price": 11.61,
      "change": 0.01,
      "voturnover": 1,
      "vaturnover": 1161
    },
    {
      "time": "14:40:26",
      "price": 11.6,
      "change": -0.01,
      "voturnover": 5,
      "vaturnover": 5800
    },
    {
      "time": "14:40:14",
      "price": 11.61,
      "change": 0,
      "voturnover": 1,
      "vaturnover": 1161
    },
    {
      "time": "14:40:08",
      "price": 11.61,
      "change": 0.01,
      "voturnover": 2,
      "vaturnover": 2322
    },
    {
      "time": "14:39:20",
      "price": 11.6,
      "change": 0,
      "voturnover": 1,
      "vaturnover": 1160
    },
    {
      "time": "14:38:50",
      "price": 11.6,
      "change": 0,
      "voturnover": 10,
      "vaturnover": 11600
    },
    {
      "time": "14:38:41",
      "price": 11.6,
      "change": -0.01,
      "voturnover": 3,
      "vaturnover": 3480
    },
    {
      "time": "14:38:38",
      "price": 11.61,
      "change": 0,
      "voturnover": 40,
      "vaturnover": 46440
    },
    {
      "time": "14:38:20",
      "price": 11.61,
      "change": 0,
      "voturnover": 5,
      "vaturnover": 5805
    },
    {
      "time": "14:38:11",
      "price": 11.61,
      "change": 0,
      "voturnover": 2,
      "vaturnover": 2322
    },
    {
      "time": "14:38:08",
      "price": 11.61,
      "change": 0.01,
      "voturnover": 1,
      "vaturnover": 1161
    },
    {
      "time": "14:38:05",
      "price": 11.6,
      "change": -0.01,
      "voturnover": 3,
      "vaturnover": 3480
    },
    {
      "time": "14:38:02",
      "price": 11.61,
      "change": 0,
      "voturnover": 1,
      "vaturnover": 1161
    },
    {
      "time": "14:37:59",
      "price": 11.61,
      "change": 0,
      "voturnover": 90,
      "vaturnover": 104490
    },
    {
      "time": "14:37:02",
      "price": 11.61,
      "change": -0.01,
      "voturnover": 17,
      "vaturnover": 19737
    },
    {
      "time": "14:35:11",
      "price": 11.62,
      "change": 0.01,
      "voturnover": 2,
      "vaturnover": 2324
    },
    {
      "time": "14:34:02",
      "price": 11.61,
      "change": 11.61,
      "voturnover": 3,
      "vaturnover": 3483
    },
    {
      "time": "14:31:23",
      "price": 11.62,
      "change": 0,
      "voturnover": 4,
      "vaturnover": 4648
    },
    {
      "time": "14:31:14",
      "price": 11.62,
      "change": 0,
      "voturnover": 20,
      "vaturnover": 23240
    },
    {
      "time": "14:30:08",
      "price": 11.62,
      "change": 0,
      "voturnover": 2,
      "vaturnover": 2324
    },
    {
      "time": "14:30:05",
      "price": 11.62,
      "change": -0.01,
      "voturnover": 2,
      "vaturnover": 2324
    },
    {
      "time": "14:25:53",
      "price": 11.63,
      "change": -0.01,
      "voturnover": 10,
      "vaturnover": 11630
    },
    {
      "time": "14:25:41",
      "price": 11.64,
      "change": 0,
      "voturnover": 0,
      "vaturnover": 0
    },
    {
      "time": "14:25:38",
      "price": 11.64,
      "change": 0,
      "voturnover": 0,
      "vaturnover": 0
    },
    {
      "time": "14:25:35",
      "price": 11.64,
      "change": 0,
      "voturnover": 0,
      "vaturnover": 0
    },
    {
      "time": "14:25:26",
      "price": 11.64,
      "change": 0,
      "voturnover": 8,
      "vaturnover": 9312
    },
    {
      "time": "14:25:08",
      "price": 11.64,
      "change": 0,
      "voturnover": 1,
      "vaturnover": 1164
    },
    {
      "time": "14:24:53",
      "price": 11.64,
      "change": 0,
      "voturnover": 0,
      "vaturnover": 0
    },
    {
      "time": "14:24:35",
      "price": 11.64,
      "change": 0.01,
      "voturnover": 8,
      "vaturnover": 9312
    },
    {
      "time": "14:24:26",
      "price": 11.63,
      "change": 0,
      "voturnover": 20,
      "vaturnover": 23260
    },
    {
      "time": "14:23:05",
      "price": 11.63,
      "change": -0.01,
      "voturnover": 20,
      "vaturnover": 23260
    },
    {
      "time": "14:21:32",
      "price": 11.64,
      "change": 0,
      "voturnover": 2,
      "vaturnover": 2328
    },
    {
      "time": "14:21:02",
      "price": 11.64,
      "change": 0.01,
      "voturnover": 3,
      "vaturnover": 3492
    },
    {
      "time": "14:20:53",
      "price": 11.63,
      "change": -0.01,
      "voturnover": 20,
      "vaturnover": 23260
    },
    {
      "time": "14:20:50",
      "price": 11.64,
      "change": 0,
      "voturnover": 1,
      "vaturnover": 1164
    },
    {
      "time": "14:20:47",
      "price": 11.64,
      "change": 0,
      "voturnover": 1,
      "vaturnover": 1164
    },
    {
      "time": "14:20:44",
      "price": 11.64,
      "change": 0,
      "voturnover": 1,
      "vaturnover": 1164
    },
    {
      "time": "14:20:41",
      "price": 11.64,
      "change": 0.01,
      "voturnover": 1,
      "vaturnover": 1164
    },
    {
      "time": "14:20:29",
      "price": 11.63,
      "change": 0,
      "voturnover": 2,
      "vaturnover": 2326
    },
    {
      "time": "14:20:26",
      "price": 11.63,
      "change": 0.01,
      "voturnover": 1,
      "vaturnover": 1163
    },
    {
      "time": "14:18:56",
      "price": 11.62,
      "change": 0,
      "voturnover": 1,
      "vaturnover": 1162
    },
    {
      "time": "14:18:44",
      "price": 11.62,
      "change": -0.02,
      "voturnover": 4,
      "vaturnover": 4648
    },
    {
      "time": "14:17:59",
      "price": 11.64,
      "change": 0.02,
      "voturnover": 8,
      "vaturnover": 9312
    },
    {
      "time": "14:16:02",
      "price": 11.62,
      "change": 0,
      "voturnover": 3,
      "vaturnover": 3486
    },
    {
      "time": "14:15:44",
      "price": 11.62,
      "change": 0,
      "voturnover": 10,
      "vaturnover": 11620
    },
    {
      "time": "14:15:32",
      "price": 11.62,
      "change": -0.02,
      "voturnover": 2,
      "vaturnover": 2324
    },
    {
      "time": "14:11:02",
      "price": 11.64,
      "change": 0.01,
      "voturnover": 8,
      "vaturnover": 9312
    },
    {
      "time": "14:08:53",
      "price": 11.63,
      "change": 0,
      "voturnover": 0,
      "vaturnover": 0
    },
    {
      "time": "14:08:23",
      "price": 11.63,
      "change": 0,
      "voturnover": 0,
      "vaturnover": 0
    },
    {
      "time": "14:07:02",
      "price": 11.63,
      "change": 0,
      "voturnover": 1,
      "vaturnover": 1163
    },
    {
      "time": "14:06:59",
      "price": 11.63,
      "change": 11.63,
      "voturnover": 3,
      "vaturnover": 3489
    },
    {
      "time": "14:05:23",
      "price": 11.62,
      "change": -0.01,
      "voturnover": 2,
      "vaturnover": 2324
    },
    {
      "time": "14:05:20",
      "price": 11.63,
      "change": 0,
      "voturnover": 0,
      "vaturnover": 0
    },
    {
      "time": "14:05:11",
      "price": 11.63,
      "change": 0,
      "voturnover": 1,
      "vaturnover": 1163
    },
    {
      "time": "14:05:08",
      "price": 11.63,
      "change": 0,
      "voturnover": 3,
      "vaturnover": 3489
    },
    {
      "time": "14:05:05",
      "price": 11.63,
      "change": 0,
      "voturnover": 3,
      "vaturnover": 3489
    },
    {
      "time": "14:05:02",
      "price": 11.63,
      "change": 0,
      "voturnover": 7,
      "vaturnover": 8141
    },
    {
      "time": "14:04:44",
      "price": 11.63,
      "change": 0.01,
      "voturnover": 1,
      "vaturnover": 1163
    },
    {
      "time": "14:04:41",
      "price": 11.62,
      "change": 0,
      "voturnover": 0,
      "vaturnover": 0
    },
    {
      "time": "14:02:44",
      "price": 11.62,
      "change": 0,
      "voturnover": 1,
      "vaturnover": 1162
    },
    {
      "time": "14:02:41",
      "price": 11.62,
      "change": 0,
      "voturnover": 3,
      "vaturnover": 3486
    },
    {
      "time": "14:01:32",
      "price": 11.62,
      "change": 0,
      "voturnover": 1,
      "vaturnover": 1162
    },
    {
      "time": "14:01:29",
      "price": 11.62,
      "change": 0,
      "voturnover": 0,
      "vaturnover": 0
    },
    {
      "time": "14:00:59",
      "price": 11.62,
      "change": 0.01,
      "voturnover": 1,
      "vaturnover": 1162
    },
    {
      "time": "13:59:47",
      "price": 11.61,
      "change": -0.01,
      "voturnover": 1,
      "vaturnover": 1161
    },
    {
      "time": "13:59:26",
      "price": 11.62,
      "change": 0,
      "voturnover": 0,
      "vaturnover": 0
    },
    {
      "time": "13:59:23",
      "price": 11.62,
      "change": 0,
      "voturnover": 1,
      "vaturnover": 1162
    },
    {
      "time": "13:59:20",
      "price": 11.62,
      "change": 0,
      "voturnover": 1,
      "vaturnover": 1162
    },
    {
      "time": "13:59:17",
      "price": 11.62,
      "change": 0.02,
      "voturnover": 3,
      "vaturnover": 3486
    },
    {
      "time": "13:58:32",
      "price": 11.6,
      "change": -0.01,
      "voturnover": 8,
      "vaturnover": 9280
    },
    {
      "time": "13:58:29",
      "price": 11.61,
      "change": 0,
      "voturnover": 10,
      "vaturnover": 11610
    },
    {
      "time": "13:57:47",
      "price": 11.61,
      "change": 0,
      "voturnover": 3,
      "vaturnover": 3483
    },
    {
      "time": "13:57:44",
      "price": 11.61,
      "change": -0.01,
      "voturnover": 13,
      "vaturnover": 15093
    },
    {
      "time": "13:55:56",
      "price": 11.62,
      "change": 0,
      "voturnover": 3,
      "vaturnover": 3486
    },
    {
      "time": "13:55:53",
      "price": 11.62,
      "change": 0.01,
      "voturnover": 5,
      "vaturnover": 5810
    },
    {
      "time": "13:54:14",
      "price": 11.61,
      "change": -0.01,
      "voturnover": 8,
      "vaturnover": 9288
    },
    {
      "time": "13:54:11",
      "price": 11.62,
      "change": 0,
      "voturnover": 5,
      "vaturnover": 5810
    },
    {
      "time": "13:54:02",
      "price": 11.62,
      "change": 0.01,
      "voturnover": 1,
      "vaturnover": 1162
    },
    {
      "time": "13:51:38",
      "price": 11.61,
      "change": 0,
      "voturnover": 2,
      "vaturnover": 2322
    },
    {
      "time": "13:51:35",
      "price": 11.61,
      "change": -0.01,
      "voturnover": 2,
      "vaturnover": 2322
    },
    {
      "time": "13:51:02",
      "price": 11.62,
      "change": 0,
      "voturnover": 0,
      "vaturnover": 0
    },
    {
      "time": "13:50:29",
      "price": 11.62,
      "change": 0,
      "voturnover": 3,
      "vaturnover": 3486
    },
    {
      "time": "13:49:32",
      "price": 11.62,
      "change": 0.01,
      "voturnover": 8,
      "vaturnover": 9296
    },
    {
      "time": "13:49:23",
      "price": 11.61,
      "change": 0,
      "voturnover": 0,
      "vaturnover": 0
    },
    {
      "time": "13:45:26",
      "price": 11.61,
      "change": 0,
      "voturnover": 6,
      "vaturnover": 6966
    },
    {
      "time": "13:44:11",
      "price": 11.61,
      "change": 0.01,
      "voturnover": 4,
      "vaturnover": 4644
    },
    {
      "time": "13:44:08",
      "price": 11.6,
      "change": 0,
      "voturnover": 6,
      "vaturnover": 6960
    },
    {
      "time": "13:44:05",
      "price": 11.6,
      "change": 0,
      "voturnover": 28,
      "vaturnover": 32480
    },
    {
      "time": "13:44:02",
      "price": 11.6,
      "change": 0,
      "voturnover": 2,
      "vaturnover": 2320
    },
    {
      "time": "13:43:59",
      "price": 11.6,
      "change": 0,
      "voturnover": 50,
      "vaturnover": 58000
    },
    {
      "time": "13:43:26",
      "price": 11.6,
      "change": 0,
      "voturnover": 4,
      "vaturnover": 4640
    },
    {
      "time": "13:43:20",
      "price": 11.6,
      "change": 0,
      "voturnover": 3,
      "vaturnover": 3480
    },
    {
      "time": "13:43:02",
      "price": 11.6,
      "change": 0,
      "voturnover": 3,
      "vaturnover": 3480
    },
    {
      "time": "13:42:56",
      "price": 11.6,
      "change": 0,
      "voturnover": 10,
      "vaturnover": 11600
    },
    {
      "time": "13:41:50",
      "price": 11.6,
      "change": 0,
      "voturnover": 1,
      "vaturnover": 1160
    },
    {
      "time": "13:41:32",
      "price": 11.6,
      "change": 0.01,
      "voturnover": 2,
      "vaturnover": 2320
    },
    {
      "time": "13:41:23",
      "price": 11.59,
      "change": -0.01,
      "voturnover": 1,
      "vaturnover": 1159
    },
    {
      "time": "13:40:53",
      "price": 11.6,
      "change": 11.6,
      "voturnover": 11,
      "vaturnover": 12760
    },
    {
      "time": "13:37:32",
      "price": 11.6,
      "change": 0.01,
      "voturnover": 2,
      "vaturnover": 2320
    },
    {
      "time": "13:36:59",
      "price": 11.59,
      "change": -0.01,
      "voturnover": 31,
      "vaturnover": 35929
    },
    {
      "time": "13:36:32",
      "price": 11.6,
      "change": 0.01,
      "voturnover": 5,
      "vaturnover": 5800
    },
    {
      "time": "13:35:08",
      "price": 11.59,
      "change": -0.01,
      "voturnover": 1,
      "vaturnover": 1159
    },
    {
      "time": "13:35:05",
      "price": 11.6,
      "change": 0,
      "voturnover": 3,
      "vaturnover": 3480
    },
    {
      "time": "13:33:29",
      "price": 11.6,
      "change": -0.02,
      "voturnover": 5,
      "vaturnover": 5800
    },
    {
      "time": "13:33:11",
      "price": 11.62,
      "change": 0.02,
      "voturnover": 8,
      "vaturnover": 9296
    },
    {
      "time": "13:27:08",
      "price": 11.6,
      "change": 0,
      "voturnover": 8,
      "vaturnover": 9280
    },
    {
      "time": "13:27:05",
      "price": 11.6,
      "change": 0,
      "voturnover": 2,
      "vaturnover": 2320
    },
    {
      "time": "13:24:32",
      "price": 11.6,
      "change": -0.02,
      "voturnover": 10,
      "vaturnover": 11600
    },
    {
      "time": "13:23:32",
      "price": 11.62,
      "change": 0.02,
      "voturnover": 10,
      "vaturnover": 11620
    },
    {
      "time": "13:22:59",
      "price": 11.6,
      "change": 0,
      "voturnover": 7,
      "vaturnover": 8120
    },
    {
      "time": "13:20:50",
      "price": 11.6,
      "change": 0,
      "voturnover": 1,
      "vaturnover": 1160
    },
    {
      "time": "13:20:47",
      "price": 11.6,
      "change": 0,
      "voturnover": 2,
      "vaturnover": 2320
    },
    {
      "time": "13:20:44",
      "price": 11.6,
      "change": 0,
      "voturnover": 2,
      "vaturnover": 2320
    },
    {
      "time": "13:20:41",
      "price": 11.6,
      "change": 0,
      "voturnover": 2,
      "vaturnover": 2320
    },
    {
      "time": "13:20:38",
      "price": 11.6,
      "change": 0,
      "voturnover": 10,
      "vaturnover": 11600
    },
    {
      "time": "13:20:35",
      "price": 11.6,
      "change": 0,
      "voturnover": 8,
      "vaturnover": 9280
    },
    {
      "time": "13:20:32",
      "price": 11.6,
      "change": 0,
      "voturnover": 5,
      "vaturnover": 5800
    },
    {
      "time": "13:19:08",
      "price": 11.6,
      "change": 0,
      "voturnover": 6,
      "vaturnover": 6960
    },
    {
      "time": "13:15:17",
      "price": 11.6,
      "change": -0.01,
      "voturnover": 1,
      "vaturnover": 1160
    },
    {
      "time": "13:15:14",
      "price": 11.61,
      "change": 0,
      "voturnover": 0,
      "vaturnover": 0
    },
    {
      "time": "13:14:59",
      "price": 11.61,
      "change": 0.01,
      "voturnover": 2,
      "vaturnover": 2322
    },
    {
      "time": "13:14:44",
      "price": 11.6,
      "change": -0.01,
      "voturnover": 10,
      "vaturnover": 11600
    },
    {
      "time": "13:14:41",
      "price": 11.61,
      "change": -0.01,
      "voturnover": 7,
      "vaturnover": 8127
    },
    {
      "time": "13:14:26",
      "price": 11.62,
      "change": 0,
      "voturnover": 0,
      "vaturnover": 0
    },
    {
      "time": "13:13:26",
      "price": 11.62,
      "change": 11.62,
      "voturnover": 8,
      "vaturnover": 9296
    },
    {
      "time": "13:09:14",
      "price": 11.58,
      "change": -0.04,
      "voturnover": 1,
      "vaturnover": 1158
    },
    {
      "time": "13:07:08",
      "price": 11.62,
      "change": 0.02,
      "voturnover": 7,
      "vaturnover": 8134
    },
    {
      "time": "13:05:59",
      "price": 11.6,
      "change": 0,
      "voturnover": 1,
      "vaturnover": 1160
    },
    {
      "time": "13:05:14",
      "price": 11.6,
      "change": 0,
      "voturnover": 1,
      "vaturnover": 1160
    },
    {
      "time": "13:02:41",
      "price": 11.6,
      "change": 0,
      "voturnover": 1,
      "vaturnover": 1160
    },
    {
      "time": "13:02:38",
      "price": 11.6,
      "change": -0.02,
      "voturnover": 1,
      "vaturnover": 1160
    },
    {
      "time": "13:02:35",
      "price": 11.62,
      "change": 0,
      "voturnover": 0,
      "vaturnover": 0
    },
    {
      "time": "13:02:02",
      "price": 11.62,
      "change": 0,
      "voturnover": 1,
      "vaturnover": 1162
    },
    {
      "time": "13:01:59",
      "price": 11.62,
      "change": 0,
      "voturnover": 2,
      "vaturnover": 2324
    },
    {
      "time": "13:00:08",
      "price": 11.62,
      "change": 0.04,
      "voturnover": 4,
      "vaturnover": 4648
    },
    {
      "time": "13:00:02",
      "price": 11.58,
      "change": 0,
      "voturnover": 10,
      "vaturnover": 11580
    },
    {
      "time": "11:29:43",
      "price": 11.58,
      "change": -0.04,
      "voturnover": 5,
      "vaturnover": 5790
    },
    {
      "time": "11:27:16",
      "price": 11.62,
      "change": 0,
      "voturnover": 3,
      "vaturnover": 3486
    },
    {
      "time": "11:27:13",
      "price": 11.62,
      "change": 0,
      "voturnover": 4,
      "vaturnover": 4648
    },
    {
      "time": "11:27:10",
      "price": 11.62,
      "change": 0,
      "voturnover": 4,
      "vaturnover": 4648
    },
    {
      "time": "11:27:07",
      "price": 11.62,
      "change": 0,
      "voturnover": 4,
      "vaturnover": 4648
    },
    {
      "time": "11:27:04",
      "price": 11.62,
      "change": 0,
      "voturnover": 10,
      "vaturnover": 11620
    },
    {
      "time": "11:25:46",
      "price": 11.62,
      "change": 0.02,
      "voturnover": 6,
      "vaturnover": 6972
    },
    {
      "time": "11:21:22",
      "price": 11.6,
      "change": 0,
      "voturnover": 10,
      "vaturnover": 11600
    },
    {
      "time": "11:20:52",
      "price": 11.6,
      "change": -0.02,
      "voturnover": 32,
      "vaturnover": 37120
    },
    {
      "time": "11:18:52",
      "price": 11.62,
      "change": 0,
      "voturnover": 1,
      "vaturnover": 1162
    },
    {
      "time": "11:16:04",
      "price": 11.62,
      "change": 0,
      "voturnover": 4,
      "vaturnover": 4648
    },
    {
      "time": "11:16:01",
      "price": 11.62,
      "change": 0,
      "voturnover": 1,
      "vaturnover": 1162
    },
    {
      "time": "11:15:58",
      "price": 11.62,
      "change": 0,
      "voturnover": 8,
      "vaturnover": 9296
    },
    {
      "time": "11:15:49",
      "price": 11.62,
      "change": 0,
      "voturnover": 8,
      "vaturnover": 9296
    },
    {
      "time": "11:15:28",
      "price": 11.62,
      "change": 0.02,
      "voturnover": 1,
      "vaturnover": 1162
    },
    {
      "time": "11:15:25",
      "price": 11.6,
      "change": 11.6,
      "voturnover": 42,
      "vaturnover": 48720
    },
    {
      "time": "11:12:22",
      "price": 11.58,
      "change": -0.02,
      "voturnover": 1,
      "vaturnover": 1158
    },
    {
      "time": "11:09:49",
      "price": 11.6,
      "change": 0,
      "voturnover": 3,
      "vaturnover": 3480
    },
    {
      "time": "11:09:25",
      "price": 11.6,
      "change": 0,
      "voturnover": 0,
      "vaturnover": 0
    },
    {
      "time": "11:09:19",
      "price": 11.6,
      "change": 0,
      "voturnover": 0,
      "vaturnover": 0
    },
    {
      "time": "11:08:34",
      "price": 11.6,
      "change": 0,
      "voturnover": 10,
      "vaturnover": 11600
    },
    {
      "time": "11:06:25",
      "price": 11.6,
      "change": 0,
      "voturnover": 8,
      "vaturnover": 9280
    },
    {
      "time": "11:06:22",
      "price": 11.6,
      "change": 0,
      "voturnover": 3,
      "vaturnover": 3480
    },
    {
      "time": "11:03:01",
      "price": 11.6,
      "change": 0,
      "voturnover": 19,
      "vaturnover": 22040
    },
    {
      "time": "11:02:52",
      "price": 11.6,
      "change": -0.02,
      "voturnover": 30,
      "vaturnover": 34800
    },
    {
      "time": "11:01:40",
      "price": 11.62,
      "change": 0.02,
      "voturnover": 1,
      "vaturnover": 1162
    },
    {
      "time": "11:01:37",
      "price": 11.6,
      "change": 0.02,
      "voturnover": 52,
      "vaturnover": 60320
    },
    {
      "time": "11:01:34",
      "price": 11.58,
      "change": -0.02,
      "voturnover": 16,
      "vaturnover": 18528
    },
    {
      "time": "11:01:25",
      "price": 11.6,
      "change": 0,
      "voturnover": 1,
      "vaturnover": 1160
    },
    {
      "time": "11:01:22",
      "price": 11.6,
      "change": 0,
      "voturnover": 3,
      "vaturnover": 3480
    },
    {
      "time": "11:00:52",
      "price": 11.6,
      "change": 0,
      "voturnover": 8,
      "vaturnover": 9280
    },
    {
      "time": "11:00:49",
      "price": 11.6,
      "change": -0.02,
      "voturnover": 36,
      "vaturnover": 41760
    },
    {
      "time": "10:59:16",
      "price": 11.62,
      "change": 0.02,
      "voturnover": 6,
      "vaturnover": 6972
    },
    {
      "time": "10:58:49",
      "price": 11.6,
      "change": 0,
      "voturnover": 2,
      "vaturnover": 2320
    },
    {
      "time": "10:58:46",
      "price": 11.6,
      "change": 0,
      "voturnover": 0,
      "vaturnover": 0
    },
    {
      "time": "10:58:37",
      "price": 11.6,
      "change": 0,
      "voturnover": 1,
      "vaturnover": 1160
    },
    {
      "time": "10:57:10",
      "price": 11.6,
      "change": -0.03,
      "voturnover": 38,
      "vaturnover": 44080
    },
    {
      "time": "10:56:52",
      "price": 11.63,
      "change": 0,
      "voturnover": 0,
      "vaturnover": 0
    },
    {
      "time": "10:55:55",
      "price": 11.63,
      "change": 0.01,
      "voturnover": 118,
      "vaturnover": 137234
    },
    {
      "time": "10:54:55",
      "price": 11.62,
      "change": 0,
      "voturnover": 0,
      "vaturnover": 0
    },
    {
      "time": "10:54:52",
      "price": 11.62,
      "change": 0,
      "voturnover": 5,
      "vaturnover": 5810
    },
    {
      "time": "10:54:49",
      "price": 11.62,
      "change": 0.03,
      "voturnover": 42,
      "vaturnover": 48804
    },
    {
      "time": "10:54:22",
      "price": 11.59,
      "change": 0,
      "voturnover": 22,
      "vaturnover": 25498
    },
    {
      "time": "10:54:19",
      "price": 11.59,
      "change": -0.03,
      "voturnover": 19,
      "vaturnover": 22021
    },
    {
      "time": "10:53:52",
      "price": 11.62,
      "change": 0,
      "voturnover": 20,
      "vaturnover": 23240
    },
    {
      "time": "10:52:34",
      "price": 11.62,
      "change": 0,
      "voturnover": 0,
      "vaturnover": 0
    },
    {
      "time": "10:51:13",
      "price": 11.62,
      "change": 0,
      "voturnover": 0,
      "vaturnover": 0
    },
    {
      "time": "10:49:25",
      "price": 11.62,
      "change": 0,
      "voturnover": 13,
      "vaturnover": 15106
    },
    {
      "time": "10:49:22",
      "price": 11.62,
      "change": 0,
      "voturnover": 10,
      "vaturnover": 11620
    },
    {
      "time": "10:49:16",
      "price": 11.62,
      "change": 0,
      "voturnover": 4,
      "vaturnover": 4648
    },
    {
      "time": "10:48:31",
      "price": 11.62,
      "change": 0,
      "voturnover": 12,
      "vaturnover": 13944
    },
    {
      "time": "10:48:22",
      "price": 11.62,
      "change": 0,
      "voturnover": 50,
      "vaturnover": 58100
    },
    {
      "time": "10:48:07",
      "price": 11.62,
      "change": -0.02,
      "voturnover": 4,
      "vaturnover": 4648
    },
    {
      "time": "10:48:04",
      "price": 11.64,
      "change": 0,
      "voturnover": 0,
      "vaturnover": 0
    },
    {
      "time": "10:47:37",
      "price": 11.64,
      "change": 11.64,
      "voturnover": 38,
      "vaturnover": 44232
    },
    {
      "time": "10:46:07",
      "price": 11.63,
      "change": 0,
      "voturnover": 1,
      "vaturnover": 1163
    },
    {
      "time": "10:46:04",
      "price": 11.63,
      "change": 0,
      "voturnover": 1,
      "vaturnover": 1163
    },
    {
      "time": "10:44:19",
      "price": 11.63,
      "change": 0,
      "voturnover": 1,
      "vaturnover": 1163
    },
    {
      "time": "10:43:37",
      "price": 11.63,
      "change": -0.01,
      "voturnover": 7,
      "vaturnover": 8141
    },
    {
      "time": "10:42:22",
      "price": 11.64,
      "change": 0.01,
      "voturnover": 1,
      "vaturnover": 1164
    },
    {
      "time": "10:42:19",
      "price": 11.63,
      "change": 0,
      "voturnover": 2,
      "vaturnover": 2326
    },
    {
      "time": "10:42:16",
      "price": 11.63,
      "change": 0,
      "voturnover": 1,
      "vaturnover": 1163
    },
    {
      "time": "10:42:13",
      "price": 11.63,
      "change": 0,
      "voturnover": 3,
      "vaturnover": 3489
    },
    {
      "time": "10:42:10",
      "price": 11.63,
      "change": 0.05,
      "voturnover": 12,
      "vaturnover": 13956
    },
    {
      "time": "10:38:04",
      "price": 11.58,
      "change": -0.02,
      "voturnover": 3,
      "vaturnover": 3474
    },
    {
      "time": "10:36:40",
      "price": 11.6,
      "change": 0,
      "voturnover": 0,
      "vaturnover": 0
    },
    {
      "time": "10:36:37",
      "price": 11.6,
      "change": 0,
      "voturnover": 0,
      "vaturnover": 0
    },
    {
      "time": "10:36:19",
      "price": 11.6,
      "change": 0,
      "voturnover": 3,
      "vaturnover": 3480
    },
    {
      "time": "10:36:13",
      "price": 11.6,
      "change": 0,
      "voturnover": 0,
      "vaturnover": 0
    },
    {
      "time": "10:36:01",
      "price": 11.6,
      "change": 0.02,
      "voturnover": 7,
      "vaturnover": 8120
    },
    {
      "time": "10:35:40",
      "price": 11.58,
      "change": 0.01,
      "voturnover": 3,
      "vaturnover": 3474
    },
    {
      "time": "10:35:22",
      "price": 11.57,
      "change": -0.01,
      "voturnover": 18,
      "vaturnover": 20826
    },
    {
      "time": "10:35:16",
      "price": 11.58,
      "change": 0,
      "voturnover": 1,
      "vaturnover": 1158
    },
    {
      "time": "10:35:13",
      "price": 11.58,
      "change": 0,
      "voturnover": 8,
      "vaturnover": 9264
    },
    {
      "time": "10:35:10",
      "price": 11.58,
      "change": 0,
      "voturnover": 0,
      "vaturnover": 0
    },
    {
      "time": "10:34:49",
      "price": 11.58,
      "change": 0.01,
      "voturnover": 1,
      "vaturnover": 1158
    },
    {
      "time": "10:33:34",
      "price": 11.57,
      "change": -0.01,
      "voturnover": 14,
      "vaturnover": 16198
    },
    {
      "time": "10:33:25",
      "price": 11.58,
      "change": -0.01,
      "voturnover": 43,
      "vaturnover": 49794
    },
    {
      "time": "10:31:01",
      "price": 11.59,
      "change": 0,
      "voturnover": 7,
      "vaturnover": 8113
    },
    {
      "time": "10:30:58",
      "price": 11.59,
      "change": 0,
      "voturnover": 14,
      "vaturnover": 16226
    },
    {
      "time": "10:29:43",
      "price": 11.59,
      "change": 0,
      "voturnover": 0,
      "vaturnover": 0
    },
    {
      "time": "10:28:52",
      "price": 11.59,
      "change": 0,
      "voturnover": 1,
      "vaturnover": 1159
    },
    {
      "time": "10:28:16",
      "price": 11.59,
      "change": -0.01,
      "voturnover": 21,
      "vaturnover": 24339
    },
    {
      "time": "10:28:13",
      "price": 11.6,
      "change": 0,
      "voturnover": 3,
      "vaturnover": 3480
    },
    {
      "time": "10:28:01",
      "price": 11.6,
      "change": 0,
      "voturnover": 1,
      "vaturnover": 1160
    },
    {
      "time": "10:27:58",
      "price": 11.6,
      "change": -0.02,
      "voturnover": 6,
      "vaturnover": 6960
    },
    {
      "time": "10:27:04",
      "price": 11.62,
      "change": 0,
      "voturnover": 0,
      "vaturnover": 0
    },
    {
      "time": "10:27:01",
      "price": 11.62,
      "change": 0.01,
      "voturnover": 1,
      "vaturnover": 1162
    },
    {
      "time": "10:26:01",
      "price": 11.61,
      "change": 0,
      "voturnover": 0,
      "vaturnover": 0
    },
    {
      "time": "10:25:58",
      "price": 11.61,
      "change": 0,
      "voturnover": 1,
      "vaturnover": 1161
    },
    {
      "time": "10:25:55",
      "price": 11.61,
      "change": 0,
      "voturnover": 4,
      "vaturnover": 4644
    },
    {
      "time": "10:25:46",
      "price": 11.61,
      "change": 0.04,
      "voturnover": 4,
      "vaturnover": 4644
    },
    {
      "time": "10:24:46",
      "price": 11.57,
      "change": 0,
      "voturnover": 0,
      "vaturnover": 0
    },
    {
      "time": "10:23:49",
      "price": 11.57,
      "change": 0,
      "voturnover": 0,
      "vaturnover": 0
    },
    {
      "time": "10:23:43",
      "price": 11.57,
      "change": 0,
      "voturnover": 12,
      "vaturnover": 13884
    },
    {
      "time": "10:23:34",
      "price": 11.57,
      "change": -0.04,
      "voturnover": 28,
      "vaturnover": 32396
    },
    {
      "time": "10:23:31",
      "price": 11.61,
      "change": 0,
      "voturnover": 0,
      "vaturnover": 0
    },
    {
      "time": "10:22:37",
      "price": 11.61,
      "change": 0,
      "voturnover": 1,
      "vaturnover": 1161
    },
    {
      "time": "10:22:01",
      "price": 11.61,
      "change": 0.05,
      "voturnover": 1,
      "vaturnover": 1161
    },
    {
      "time": "10:21:37",
      "price": 11.56,
      "change": 0,
      "voturnover": 0,
      "vaturnover": 0
    },
    {
      "time": "10:20:40",
      "price": 11.56,
      "change": 0,
      "voturnover": 0,
      "vaturnover": 0
    },
    {
      "time": "10:20:01",
      "price": 11.56,
      "change": 11.56,
      "voturnover": 0,
      "vaturnover": 0
    },
    {
      "time": "10:18:49",
      "price": 11.56,
      "change": 0,
      "voturnover": 13,
      "vaturnover": 15028
    },
    {
      "time": "10:18:43",
      "price": 11.56,
      "change": -0.04,
      "voturnover": 14,
      "vaturnover": 16184
    },
    {
      "time": "10:16:46",
      "price": 11.6,
      "change": 0,
      "voturnover": 0,
      "vaturnover": 0
    },
    {
      "time": "10:16:19",
      "price": 11.6,
      "change": 0.01,
      "voturnover": 9,
      "vaturnover": 10440
    },
    {
      "time": "10:16:16",
      "price": 11.59,
      "change": 0,
      "voturnover": 0,
      "vaturnover": 0
    },
    {
      "time": "10:16:13",
      "price": 11.59,
      "change": 0,
      "voturnover": 10,
      "vaturnover": 11590
    },
    {
      "time": "10:15:37",
      "price": 11.59,
      "change": -0.01,
      "voturnover": 1,
      "vaturnover": 1159
    },
    {
      "time": "10:15:28",
      "price": 11.6,
      "change": 0,
      "voturnover": 4,
      "vaturnover": 4640
    },
    {
      "time": "10:14:34",
      "price": 11.6,
      "change": 0,
      "voturnover": 0,
      "vaturnover": 0
    },
    {
      "time": "10:14:07",
      "price": 11.6,
      "change": 0,
      "voturnover": 0,
      "vaturnover": 0
    },
    {
      "time": "10:14:01",
      "price": 11.6,
      "change": 0,
      "voturnover": 1,
      "vaturnover": 1160
    },
    {
      "time": "10:13:04",
      "price": 11.6,
      "change": -0.01,
      "voturnover": 12,
      "vaturnover": 13920
    },
    {
      "time": "10:12:43",
      "price": 11.61,
      "change": 0,
      "voturnover": 1,
      "vaturnover": 1161
    },
    {
      "time": "10:12:40",
      "price": 11.61,
      "change": 0.01,
      "voturnover": 1,
      "vaturnover": 1161
    },
    {
      "time": "10:12:37",
      "price": 11.6,
      "change": 0,
      "voturnover": 4,
      "vaturnover": 4640
    },
    {
      "time": "10:12:34",
      "price": 11.6,
      "change": 0,
      "voturnover": 3,
      "vaturnover": 3480
    },
    {
      "time": "10:12:31",
      "price": 11.6,
      "change": 0.02,
      "voturnover": 1,
      "vaturnover": 1160
    },
    {
      "time": "10:11:37",
      "price": 11.58,
      "change": 0,
      "voturnover": 0,
      "vaturnover": 0
    },
    {
      "time": "10:10:07",
      "price": 11.58,
      "change": 0,
      "voturnover": 0,
      "vaturnover": 0
    },
    {
      "time": "10:09:49",
      "price": 11.58,
      "change": 0,
      "voturnover": 20,
      "vaturnover": 23160
    },
    {
      "time": "10:09:22",
      "price": 11.58,
      "change": 0,
      "voturnover": 20,
      "vaturnover": 23160
    },
    {
      "time": "10:09:01",
      "price": 11.58,
      "change": 0,
      "voturnover": 1,
      "vaturnover": 1158
    },
    {
      "time": "10:08:37",
      "price": 11.58,
      "change": 0,
      "voturnover": 5,
      "vaturnover": 5790
    },
    {
      "time": "10:08:34",
      "price": 11.58,
      "change": 0,
      "voturnover": 11,
      "vaturnover": 12738
    },
    {
      "time": "10:07:25",
      "price": 11.58,
      "change": 0,
      "voturnover": 0,
      "vaturnover": 0
    },
    {
      "time": "10:07:22",
      "price": 11.58,
      "change": 0,
      "voturnover": 0,
      "vaturnover": 0
    },
    {
      "time": "10:07:19",
      "price": 11.58,
      "change": 0,
      "voturnover": 0,
      "vaturnover": 0
    },
    {
      "time": "10:07:16",
      "price": 11.58,
      "change": 0,
      "voturnover": 0,
      "vaturnover": 0
    },
    {
      "time": "10:07:13",
      "price": 11.58,
      "change": 0,
      "voturnover": 0,
      "vaturnover": 0
    },
    {
      "time": "10:07:10",
      "price": 11.58,
      "change": 0,
      "voturnover": 0,
      "vaturnover": 0
    },
    {
      "time": "10:07:07",
      "price": 11.58,
      "change": 0,
      "voturnover": 0,
      "vaturnover": 0
    },
    {
      "time": "10:07:04",
      "price": 11.58,
      "change": 0,
      "voturnover": 0,
      "vaturnover": 0
    },
    {
      "time": "10:07:01",
      "price": 11.58,
      "change": 0,
      "voturnover": 0,
      "vaturnover": 0
    },
    {
      "time": "10:06:58",
      "price": 11.58,
      "change": 0,
      "voturnover": 0,
      "vaturnover": 0
    },
    {
      "time": "10:06:55",
      "price": 11.58,
      "change": 0,
      "voturnover": 0,
      "vaturnover": 0
    },
    {
      "time": "10:06:40",
      "price": 11.58,
      "change": -0.03,
      "voturnover": 5,
      "vaturnover": 5790
    },
    {
      "time": "10:06:37",
      "price": 11.61,
      "change": 0,
      "voturnover": 0,
      "vaturnover": 0
    },
    {
      "time": "10:06:34",
      "price": 11.61,
      "change": 0,
      "voturnover": 9,
      "vaturnover": 10449
    },
    {
      "time": "10:06:31",
      "price": 11.61,
      "change": 0,
      "voturnover": 0,
      "vaturnover": 0
    },
    {
      "time": "10:06:28",
      "price": 11.61,
      "change": 0,
      "voturnover": 0,
      "vaturnover": 0
    },
    {
      "time": "10:06:25",
      "price": 11.61,
      "change": 0,
      "voturnover": 9,
      "vaturnover": 10449
    },
    {
      "time": "10:06:07",
      "price": 11.61,
      "change": 0.03,
      "voturnover": 6,
      "vaturnover": 6966
    },
    {
      "time": "10:05:10",
      "price": 11.58,
      "change": 0,
      "voturnover": 8,
      "vaturnover": 9264
    },
    {
      "time": "10:04:55",
      "price": 11.58,
      "change": 0,
      "voturnover": 3,
      "vaturnover": 3474
    },
    {
      "time": "10:04:52",
      "price": 11.58,
      "change": 0,
      "voturnover": 2,
      "vaturnover": 2316
    },
    {
      "time": "10:04:49",
      "price": 11.58,
      "change": 0.01,
      "voturnover": 2,
      "vaturnover": 2316
    },
    {
      "time": "10:04:46",
      "price": 11.57,
      "change": 0.02,
      "voturnover": 1,
      "vaturnover": 1157
    },
    {
      "time": "10:04:43",
      "price": 11.55,
      "change": 0,
      "voturnover": 4,
      "vaturnover": 4620
    },
    {
      "time": "10:04:40",
      "price": 11.55,
      "change": 0,
      "voturnover": 19,
      "vaturnover": 21945
    },
    {
      "time": "10:04:37",
      "price": 11.55,
      "change": 0.01,
      "voturnover": 1,
      "vaturnover": 1155
    },
    {
      "time": "10:04:13",
      "price": 11.54,
      "change": -0.01,
      "voturnover": 10,
      "vaturnover": 11540
    },
    {
      "time": "10:03:43",
      "price": 11.55,
      "change": 0,
      "voturnover": 2,
      "vaturnover": 2310
    },
    {
      "time": "10:03:37",
      "price": 11.55,
      "change": 0,
      "voturnover": 11,
      "vaturnover": 12705
    },
    {
      "time": "10:03:04",
      "price": 11.55,
      "change": 0,
      "voturnover": 2,
      "vaturnover": 2310
    },
    {
      "time": "10:03:01",
      "price": 11.55,
      "change": 0,
      "voturnover": 1,
      "vaturnover": 1155
    },
    {
      "time": "10:02:55",
      "price": 11.55,
      "change": 0,
      "voturnover": 10,
      "vaturnover": 11550
    },
    {
      "time": "10:02:49",
      "price": 11.55,
      "change": 0,
      "voturnover": 15,
      "vaturnover": 17325
    },
    {
      "time": "10:02:46",
      "price": 11.55,
      "change": 0,
      "voturnover": 50,
      "vaturnover": 57750
    },
    {
      "time": "10:02:22",
      "price": 11.55,
      "change": -0.01,
      "voturnover": 12,
      "vaturnover": 13860
    },
    {
      "time": "10:02:16",
      "price": 11.56,
      "change": 0,
      "voturnover": 30,
      "vaturnover": 34680
    },
    {
      "time": "10:02:01",
      "price": 11.56,
      "change": -0.01,
      "voturnover": 8,
      "vaturnover": 9248
    },
    {
      "time": "10:01:46",
      "price": 11.57,
      "change": 0,
      "voturnover": 1,
      "vaturnover": 1157
    },
    {
      "time": "10:01:40",
      "price": 11.57,
      "change": -0.01,
      "voturnover": 1,
      "vaturnover": 1157
    },
    {
      "time": "10:01:37",
      "price": 11.58,
      "change": 0.01,
      "voturnover": 9,
      "vaturnover": 10422
    },
    {
      "time": "10:01:34",
      "price": 11.57,
      "change": 0,
      "voturnover": 3,
      "vaturnover": 3471
    },
    {
      "time": "10:01:28",
      "price": 11.57,
      "change": 0,
      "voturnover": 30,
      "vaturnover": 34710
    },
    {
      "time": "10:01:25",
      "price": 11.57,
      "change": 0,
      "voturnover": 1,
      "vaturnover": 1157
    },
    {
      "time": "10:01:22",
      "price": 11.57,
      "change": 0,
      "voturnover": 9,
      "vaturnover": 10413
    },
    {
      "time": "10:01:19",
      "price": 11.57,
      "change": -0.01,
      "voturnover": 80,
      "vaturnover": 92560
    },
    {
      "time": "10:01:13",
      "price": 11.58,
      "change": 0,
      "voturnover": 45,
      "vaturnover": 52110
    },
    {
      "time": "10:00:43",
      "price": 11.58,
      "change": -0.01,
      "voturnover": 16,
      "vaturnover": 18528
    },
    {
      "time": "10:00:25",
      "price": 11.59,
      "change": 0.01,
      "voturnover": 4,
      "vaturnover": 4636
    },
    {
      "time": "10:00:22",
      "price": 11.58,
      "change": -0.01,
      "voturnover": 3,
      "vaturnover": 3474
    },
    {
      "time": "10:00:19",
      "price": 11.59,
      "change": 0,
      "voturnover": 2,
      "vaturnover": 2318
    },
    {
      "time": "10:00:16",
      "price": 11.59,
      "change": -0.01,
      "voturnover": 15,
      "vaturnover": 17385
    },
    {
      "time": "10:00:10",
      "price": 11.6,
      "change": 0.01,
      "voturnover": 2,
      "vaturnover": 2320
    },
    {
      "time": "10:00:07",
      "price": 11.59,
      "change": -0.01,
      "voturnover": 15,
      "vaturnover": 17385
    },
    {
      "time": "10:00:04",
      "price": 11.6,
      "change": 0.01,
      "voturnover": 1,
      "vaturnover": 1160
    },
    {
      "time": "09:59:04",
      "price": 11.59,
      "change": -0.01,
      "voturnover": 8,
      "vaturnover": 9272
    },
    {
      "time": "09:58:37",
      "price": 11.6,
      "change": 0.01,
      "voturnover": 1,
      "vaturnover": 1160
    },
    {
      "time": "09:58:16",
      "price": 11.59,
      "change": 0,
      "voturnover": 11,
      "vaturnover": 12749
    },
    {
      "time": "09:57:52",
      "price": 11.59,
      "change": 0,
      "voturnover": 0,
      "vaturnover": 0
    },
    {
      "time": "09:57:40",
      "price": 11.59,
      "change": 0,
      "voturnover": 0,
      "vaturnover": 0
    },
    {
      "time": "09:57:34",
      "price": 11.59,
      "change": 0,
      "voturnover": 2,
      "vaturnover": 2318
    },
    {
      "time": "09:57:00",
      "price": 11.59,
      "change": 0,
      "voturnover": 5,
      "vaturnover": 5795
    },
    {
      "time": "09:56:58",
      "price": 11.59,
      "change": 0,
      "voturnover": 16,
      "vaturnover": 18544
    },
    {
      "time": "09:55:43",
      "price": 11.59,
      "change": 0,
      "voturnover": 0,
      "vaturnover": 0
    },
    {
      "time": "09:55:40",
      "price": 11.59,
      "change": 0,
      "voturnover": 20,
      "vaturnover": 23180
    },
    {
      "time": "09:55:34",
      "price": 11.59,
      "change": 0,
      "voturnover": 10,
      "vaturnover": 11590
    },
    {
      "time": "09:55:22",
      "price": 11.59,
      "change": 0,
      "voturnover": 1,
      "vaturnover": 1159
    },
    {
      "time": "09:55:19",
      "price": 11.59,
      "change": 0,
      "voturnover": 4,
      "vaturnover": 4636
    },
    {
      "time": "09:55:16",
      "price": 11.59,
      "change": 0,
      "voturnover": 9,
      "vaturnover": 10431
    },
    {
      "time": "09:55:13",
      "price": 11.59,
      "change": 0,
      "voturnover": 17,
      "vaturnover": 19703
    },
    {
      "time": "09:54:31",
      "price": 11.59,
      "change": 0,
      "voturnover": 11,
      "vaturnover": 12749
    },
    {
      "time": "09:53:37",
      "price": 11.59,
      "change": 0.01,
      "voturnover": 1,
      "vaturnover": 1159
    },
    {
      "time": "09:53:22",
      "price": 11.58,
      "change": 0,
      "voturnover": 26,
      "vaturnover": 30108
    },
    {
      "time": "09:53:19",
      "price": 11.58,
      "change": 0,
      "voturnover": 5,
      "vaturnover": 5790
    },
    {
      "time": "09:52:28",
      "price": 11.58,
      "change": 0.01,
      "voturnover": 2,
      "vaturnover": 2316
    },
    {
      "time": "09:52:16",
      "price": 11.57,
      "change": 11.57,
      "voturnover": 7,
      "vaturnover": 8099
    },
    {
      "time": "09:52:01",
      "price": 11.58,
      "change": -0.01,
      "voturnover": 17,
      "vaturnover": 19686
    },
    {
      "time": "09:51:55",
      "price": 11.59,
      "change": 0,
      "voturnover": 7,
      "vaturnover": 8113
    },
    {
      "time": "09:51:49",
      "price": 11.59,
      "change": 0.01,
      "voturnover": 3,
      "vaturnover": 3477
    },
    {
      "time": "09:51:25",
      "price": 11.58,
      "change": 0,
      "voturnover": 3,
      "vaturnover": 3474
    },
    {
      "time": "09:51:19",
      "price": 11.58,
      "change": -0.01,
      "voturnover": 1,
      "vaturnover": 1158
    },
    {
      "time": "09:50:37",
      "price": 11.59,
      "change": 0,
      "voturnover": 9,
      "vaturnover": 10431
    },
    {
      "time": "09:50:13",
      "price": 11.59,
      "change": 0,
      "voturnover": 63,
      "vaturnover": 73017
    },
    {
      "time": "09:49:58",
      "price": 11.59,
      "change": 0.01,
      "voturnover": 3,
      "vaturnover": 3477
    },
    {
      "time": "09:48:58",
      "price": 11.58,
      "change": -0.01,
      "voturnover": 9,
      "vaturnover": 10422
    },
    {
      "time": "09:48:37",
      "price": 11.59,
      "change": 0,
      "voturnover": 1,
      "vaturnover": 1159
    },
    {
      "time": "09:48:07",
      "price": 11.59,
      "change": 0,
      "voturnover": 4,
      "vaturnover": 4636
    },
    {
      "time": "09:47:37",
      "price": 11.59,
      "change": 0,
      "voturnover": 3,
      "vaturnover": 3477
    },
    {
      "time": "09:47:34",
      "price": 11.59,
      "change": -0.01,
      "voturnover": 17,
      "vaturnover": 19703
    },
    {
      "time": "09:47:31",
      "price": 11.6,
      "change": 0.01,
      "voturnover": 15,
      "vaturnover": 17400
    },
    {
      "time": "09:47:28",
      "price": 11.59,
      "change": 0,
      "voturnover": 0,
      "vaturnover": 0
    },
    {
      "time": "09:47:25",
      "price": 11.59,
      "change": 0,
      "voturnover": 9,
      "vaturnover": 10431
    },
    {
      "time": "09:47:22",
      "price": 11.59,
      "change": 0,
      "voturnover": 0,
      "vaturnover": 0
    },
    {
      "time": "09:47:18",
      "price": 11.59,
      "change": 0,
      "voturnover": 0,
      "vaturnover": 0
    },
    {
      "time": "09:47:16",
      "price": 11.59,
      "change": 0,
      "voturnover": 0,
      "vaturnover": 0
    },
    {
      "time": "09:47:12",
      "price": 11.59,
      "change": 0,
      "voturnover": 0,
      "vaturnover": 0
    },
    {
      "time": "09:47:10",
      "price": 11.59,
      "change": 0,
      "voturnover": 0,
      "vaturnover": 0
    },
    {
      "time": "09:47:07",
      "price": 11.59,
      "change": 0,
      "voturnover": 0,
      "vaturnover": 0
    },
    {
      "time": "09:47:04",
      "price": 11.59,
      "change": 0,
      "voturnover": 0,
      "vaturnover": 0
    },
    {
      "time": "09:47:01",
      "price": 11.59,
      "change": 0,
      "voturnover": 0,
      "vaturnover": 0
    },
    {
      "time": "09:46:58",
      "price": 11.59,
      "change": 0,
      "voturnover": 0,
      "vaturnover": 0
    },
    {
      "time": "09:46:55",
      "price": 11.59,
      "change": 0,
      "voturnover": 0,
      "vaturnover": 0
    },
    {
      "time": "09:46:52",
      "price": 11.59,
      "change": 0,
      "voturnover": 0,
      "vaturnover": 0
    },
    {
      "time": "09:46:49",
      "price": 11.59,
      "change": 0,
      "voturnover": 0,
      "vaturnover": 0
    },
    {
      "time": "09:46:46",
      "price": 11.59,
      "change": 0,
      "voturnover": 0,
      "vaturnover": 0
    },
    {
      "time": "09:46:43",
      "price": 11.59,
      "change": 0,
      "voturnover": 2,
      "vaturnover": 2318
    },
    {
      "time": "09:46:40",
      "price": 11.59,
      "change": 0,
      "voturnover": 28,
      "vaturnover": 32452
    },
    {
      "time": "09:46:07",
      "price": 11.59,
      "change": 0,
      "voturnover": 0,
      "vaturnover": 0
    },
    {
      "time": "09:46:04",
      "price": 11.59,
      "change": 0,
      "voturnover": 0,
      "vaturnover": 0
    },
    {
      "time": "09:46:01",
      "price": 11.59,
      "change": -0.01,
      "voturnover": 30,
      "vaturnover": 34770
    },
    {
      "time": "09:45:58",
      "price": 11.6,
      "change": 0,
      "voturnover": 0,
      "vaturnover": 0
    },
    {
      "time": "09:45:22",
      "price": 11.6,
      "change": 0.01,
      "voturnover": 1,
      "vaturnover": 1160
    },
    {
      "time": "09:45:19",
      "price": 11.59,
      "change": -0.01,
      "voturnover": 5,
      "vaturnover": 5795
    },
    {
      "time": "09:45:16",
      "price": 11.6,
      "change": -0.01,
      "voturnover": 3,
      "vaturnover": 3480
    },
    {
      "time": "09:45:13",
      "price": 11.61,
      "change": 0,
      "voturnover": 0,
      "vaturnover": 0
    },
    {
      "time": "09:45:10",
      "price": 11.61,
      "change": -0.03,
      "voturnover": 26,
      "vaturnover": 30186
    },
    {
      "time": "09:44:37",
      "price": 11.64,
      "change": 0.01,
      "voturnover": 1,
      "vaturnover": 1164
    },
    {
      "time": "09:44:15",
      "price": 11.63,
      "change": 0,
      "voturnover": 4,
      "vaturnover": 4652
    },
    {
      "time": "09:44:07",
      "price": 11.63,
      "change": 0,
      "voturnover": 4,
      "vaturnover": 4652
    },
    {
      "time": "09:43:58",
      "price": 11.63,
      "change": 0,
      "voturnover": 1,
      "vaturnover": 1163
    },
    {
      "time": "09:43:37",
      "price": 11.63,
      "change": 0,
      "voturnover": 0,
      "vaturnover": 0
    },
    {
      "time": "09:43:18",
      "price": 11.63,
      "change": 0,
      "voturnover": 0,
      "vaturnover": 0
    },
    {
      "time": "09:43:15",
      "price": 11.63,
      "change": 0,
      "voturnover": 2,
      "vaturnover": 2326
    },
    {
      "time": "09:43:13",
      "price": 11.63,
      "change": 0,
      "voturnover": 2,
      "vaturnover": 2326
    },
    {
      "time": "09:43:07",
      "price": 11.63,
      "change": 0.03,
      "voturnover": 2,
      "vaturnover": 2326
    },
    {
      "time": "09:43:04",
      "price": 11.6,
      "change": -0.01,
      "voturnover": 101,
      "vaturnover": 117160
    },
    {
      "time": "09:43:01",
      "price": 11.61,
      "change": 0,
      "voturnover": 3,
      "vaturnover": 3483
    },
    {
      "time": "09:42:55",
      "price": 11.61,
      "change": 0,
      "voturnover": 6,
      "vaturnover": 6966
    },
    {
      "time": "09:42:52",
      "price": 11.61,
      "change": 0,
      "voturnover": 1,
      "vaturnover": 1161
    },
    {
      "time": "09:42:49",
      "price": 11.61,
      "change": 0,
      "voturnover": 6,
      "vaturnover": 6966
    },
    {
      "time": "09:42:04",
      "price": 11.61,
      "change": -0.01,
      "voturnover": 10,
      "vaturnover": 11610
    },
    {
      "time": "09:41:57",
      "price": 11.62,
      "change": 0,
      "voturnover": 0,
      "vaturnover": 0
    },
    {
      "time": "09:41:37",
      "price": 11.62,
      "change": 0,
      "voturnover": 0,
      "vaturnover": 0
    },
    {
      "time": "09:41:34",
      "price": 11.62,
      "change": 0,
      "voturnover": 0,
      "vaturnover": 0
    },
    {
      "time": "09:41:28",
      "price": 11.62,
      "change": 0,
      "voturnover": 1,
      "vaturnover": 1162
    },
    {
      "time": "09:41:01",
      "price": 11.62,
      "change": 0,
      "voturnover": 1,
      "vaturnover": 1162
    },
    {
      "time": "09:40:36",
      "price": 11.62,
      "change": 0.02,
      "voturnover": 1,
      "vaturnover": 1162
    },
    {
      "time": "09:40:03",
      "price": 11.6,
      "change": 0,
      "voturnover": 75,
      "vaturnover": 87000
    },
    {
      "time": "09:39:55",
      "price": 11.6,
      "change": 0,
      "voturnover": 2,
      "vaturnover": 2320
    },
    {
      "time": "09:39:51",
      "price": 11.6,
      "change": -0.02,
      "voturnover": 23,
      "vaturnover": 26680
    },
    {
      "time": "09:39:46",
      "price": 11.62,
      "change": 0.01,
      "voturnover": 18,
      "vaturnover": 20916
    },
    {
      "time": "09:39:43",
      "price": 11.61,
      "change": -0.01,
      "voturnover": 16,
      "vaturnover": 18576
    },
    {
      "time": "09:39:34",
      "price": 11.62,
      "change": 0.01,
      "voturnover": 6,
      "vaturnover": 6972
    },
    {
      "time": "09:39:31",
      "price": 11.61,
      "change": -0.02,
      "voturnover": 4,
      "vaturnover": 4644
    },
    {
      "time": "09:39:25",
      "price": 11.63,
      "change": 0,
      "voturnover": 0,
      "vaturnover": 0
    },
    {
      "time": "09:38:30",
      "price": 11.63,
      "change": 0,
      "voturnover": 0,
      "vaturnover": 0
    },
    {
      "time": "09:38:07",
      "price": 11.63,
      "change": 0,
      "voturnover": 1,
      "vaturnover": 1163
    },
    {
      "time": "09:38:04",
      "price": 11.63,
      "change": 0,
      "voturnover": 0,
      "vaturnover": 0
    },
    {
      "time": "09:37:58",
      "price": 11.63,
      "change": 0,
      "voturnover": 1,
      "vaturnover": 1163
    },
    {
      "time": "09:37:48",
      "price": 11.63,
      "change": 0,
      "voturnover": 1,
      "vaturnover": 1163
    },
    {
      "time": "09:37:45",
      "price": 11.63,
      "change": -0.02,
      "voturnover": 1,
      "vaturnover": 1163
    },
    {
      "time": "09:37:42",
      "price": 11.65,
      "change": -0.01,
      "voturnover": 13,
      "vaturnover": 15145
    },
    {
      "time": "09:37:36",
      "price": 11.66,
      "change": 0,
      "voturnover": 1,
      "vaturnover": 1166
    },
    {
      "time": "09:37:33",
      "price": 11.66,
      "change": 0,
      "voturnover": 1,
      "vaturnover": 1166
    },
    {
      "time": "09:37:24",
      "price": 11.66,
      "change": 0,
      "voturnover": 1,
      "vaturnover": 1166
    },
    {
      "time": "09:37:15",
      "price": 11.66,
      "change": 0.01,
      "voturnover": 1,
      "vaturnover": 1166
    },
    {
      "time": "09:37:09",
      "price": 11.65,
      "change": 0,
      "voturnover": 3,
      "vaturnover": 3495
    },
    {
      "time": "09:37:03",
      "price": 11.65,
      "change": 0,
      "voturnover": 11,
      "vaturnover": 12815
    },
    {
      "time": "09:36:48",
      "price": 11.65,
      "change": 0.02,
      "voturnover": 5,
      "vaturnover": 5825
    },
    {
      "time": "09:36:39",
      "price": 11.63,
      "change": -0.02,
      "voturnover": 3,
      "vaturnover": 3489
    },
    {
      "time": "09:36:33",
      "price": 11.65,
      "change": 0.02,
      "voturnover": 2,
      "vaturnover": 2330
    },
    {
      "time": "09:36:18",
      "price": 11.63,
      "change": -0.03,
      "voturnover": 1,
      "vaturnover": 1163
    },
    {
      "time": "09:36:00",
      "price": 11.66,
      "change": 0,
      "voturnover": 1,
      "vaturnover": 1166
    },
    {
      "time": "09:35:57",
      "price": 11.66,
      "change": 0,
      "voturnover": 0,
      "vaturnover": 0
    },
    {
      "time": "09:35:54",
      "price": 11.66,
      "change": 0,
      "voturnover": 1,
      "vaturnover": 1166
    },
    {
      "time": "09:35:51",
      "price": 11.66,
      "change": 0,
      "voturnover": 3,
      "vaturnover": 3498
    },
    {
      "time": "09:35:33",
      "price": 11.66,
      "change": 0.06,
      "voturnover": 1,
      "vaturnover": 1166
    },
    {
      "time": "09:35:30",
      "price": 11.6,
      "change": -0.06,
      "voturnover": 95,
      "vaturnover": 110200
    },
    {
      "time": "09:35:24",
      "price": 11.66,
      "change": 0,
      "voturnover": 10,
      "vaturnover": 11660
    },
    {
      "time": "09:35:15",
      "price": 11.66,
      "change": 0.01,
      "voturnover": 20,
      "vaturnover": 23320
    },
    {
      "time": "09:35:12",
      "price": 11.65,
      "change": 0,
      "voturnover": 0,
      "vaturnover": 0
    },
    {
      "time": "09:35:09",
      "price": 11.65,
      "change": 0,
      "voturnover": 0,
      "vaturnover": 0
    },
    {
      "time": "09:35:07",
      "price": 11.65,
      "change": 0,
      "voturnover": 0,
      "vaturnover": 0
    },
    {
      "time": "09:35:03",
      "price": 11.65,
      "change": 0,
      "voturnover": 0,
      "vaturnover": 0
    },
    {
      "time": "09:35:00",
      "price": 11.65,
      "change": 0,
      "voturnover": 0,
      "vaturnover": 0
    },
    {
      "time": "09:34:57",
      "price": 11.65,
      "change": 0,
      "voturnover": 0,
      "vaturnover": 0
    },
    {
      "time": "09:34:54",
      "price": 11.65,
      "change": 0.03,
      "voturnover": 2,
      "vaturnover": 2330
    },
    {
      "time": "09:34:51",
      "price": 11.62,
      "change": 0,
      "voturnover": 0,
      "vaturnover": 0
    },
    {
      "time": "09:34:48",
      "price": 11.62,
      "change": 0,
      "voturnover": 0,
      "vaturnover": 0
    },
    {
      "time": "09:34:45",
      "price": 11.62,
      "change": -0.07,
      "voturnover": 2,
      "vaturnover": 2324
    },
    {
      "time": "09:34:42",
      "price": 11.69,
      "change": 0,
      "voturnover": 0,
      "vaturnover": 0
    },
    {
      "time": "09:34:39",
      "price": 11.69,
      "change": 0,
      "voturnover": 0,
      "vaturnover": 0
    },
    {
      "time": "09:34:36",
      "price": 11.69,
      "change": 0,
      "voturnover": 0,
      "vaturnover": 0
    },
    {
      "time": "09:34:33",
      "price": 11.69,
      "change": 0,
      "voturnover": 0,
      "vaturnover": 0
    },
    {
      "time": "09:34:30",
      "price": 11.69,
      "change": 0.03,
      "voturnover": 7,
      "vaturnover": 8183
    },
    {
      "time": "09:34:27",
      "price": 11.66,
      "change": 0,
      "voturnover": 1,
      "vaturnover": 1166
    },
    {
      "time": "09:34:18",
      "price": 11.66,
      "change": 0,
      "voturnover": 1,
      "vaturnover": 1166
    },
    {
      "time": "09:34:00",
      "price": 11.66,
      "change": 0,
      "voturnover": 0,
      "vaturnover": 0
    },
    {
      "time": "09:33:57",
      "price": 11.66,
      "change": 0,
      "voturnover": 0,
      "vaturnover": 0
    },
    {
      "time": "09:33:54",
      "price": 11.66,
      "change": -0.03,
      "voturnover": 6,
      "vaturnover": 6996
    },
    {
      "time": "09:33:51",
      "price": 11.69,
      "change": 0,
      "voturnover": 0,
      "vaturnover": 0
    },
    {
      "time": "09:33:48",
      "price": 11.69,
      "change": 0,
      "voturnover": 0,
      "vaturnover": 0
    },
    {
      "time": "09:33:45",
      "price": 11.69,
      "change": 0,
      "voturnover": 3,
      "vaturnover": 3507
    },
    {
      "time": "09:33:42",
      "price": 11.69,
      "change": 0,
      "voturnover": 0,
      "vaturnover": 0
    },
    {
      "time": "09:33:39",
      "price": 11.69,
      "change": 0,
      "voturnover": 0,
      "vaturnover": 0
    },
    {
      "time": "09:33:36",
      "price": 11.69,
      "change": 0,
      "voturnover": 0,
      "vaturnover": 0
    },
    {
      "time": "09:33:33",
      "price": 11.69,
      "change": 0.04,
      "voturnover": 1,
      "vaturnover": 1169
    },
    {
      "time": "09:33:30",
      "price": 11.65,
      "change": 0,
      "voturnover": 0,
      "vaturnover": 0
    },
    {
      "time": "09:33:18",
      "price": 11.65,
      "change": 0,
      "voturnover": 2,
      "vaturnover": 2330
    },
    {
      "time": "09:33:15",
      "price": 11.65,
      "change": 0,
      "voturnover": 3,
      "vaturnover": 3495
    },
    {
      "time": "09:33:12",
      "price": 11.65,
      "change": 0,
      "voturnover": 11,
      "vaturnover": 12815
    },
    {
      "time": "09:33:03",
      "price": 11.65,
      "change": -0.03,
      "voturnover": 10,
      "vaturnover": 11650
    },
    {
      "time": "09:32:42",
      "price": 11.68,
      "change": 0,
      "voturnover": 0,
      "vaturnover": 0
    },
    {
      "time": "09:32:39",
      "price": 11.68,
      "change": 0,
      "voturnover": 0,
      "vaturnover": 0
    },
    {
      "time": "09:32:36",
      "price": 11.68,
      "change": -0.01,
      "voturnover": 1,
      "vaturnover": 1168
    },
    {
      "time": "09:32:33",
      "price": 11.69,
      "change": 0,
      "voturnover": 0,
      "vaturnover": 0
    },
    {
      "time": "09:32:30",
      "price": 11.69,
      "change": 0,
      "voturnover": 0,
      "vaturnover": 0
    },
    {
      "time": "09:32:27",
      "price": 11.69,
      "change": 0,
      "voturnover": 0,
      "vaturnover": 0
    },
    {
      "time": "09:32:24",
      "price": 11.69,
      "change": 0,
      "voturnover": 0,
      "vaturnover": 0
    },
    {
      "time": "09:32:21",
      "price": 11.69,
      "change": 0,
      "voturnover": 0,
      "vaturnover": 0
    },
    {
      "time": "09:32:18",
      "price": 11.69,
      "change": 0,
      "voturnover": 0,
      "vaturnover": 0
    },
    {
      "time": "09:32:15",
      "price": 11.69,
      "change": -0.01,
      "voturnover": 1,
      "vaturnover": 1169
    },
    {
      "time": "09:32:12",
      "price": 11.7,
      "change": 0.08,
      "voturnover": 20,
      "vaturnover": 23400
    },
    {
      "time": "09:32:09",
      "price": 11.62,
      "change": 0,
      "voturnover": 1,
      "vaturnover": 1162
    },
    {
      "time": "09:32:06",
      "price": 11.62,
      "change": 0.04,
      "voturnover": 11,
      "vaturnover": 12782
    },
    {
      "time": "09:32:03",
      "price": 11.58,
      "change": -0.04,
      "voturnover": 1,
      "vaturnover": 1158
    },
    {
      "time": "09:32:00",
      "price": 11.62,
      "change": 0,
      "voturnover": 1,
      "vaturnover": 1162
    },
    {
      "time": "09:31:57",
      "price": 11.62,
      "change": 0,
      "voturnover": 17,
      "vaturnover": 19754
    },
    {
      "time": "09:31:54",
      "price": 11.62,
      "change": 0.05,
      "voturnover": 1,
      "vaturnover": 1162
    },
    {
      "time": "09:31:51",
      "price": 11.57,
      "change": -0.05,
      "voturnover": 21,
      "vaturnover": 24297
    },
    {
      "time": "09:31:39",
      "price": 11.62,
      "change": 0.01,
      "voturnover": 20,
      "vaturnover": 23240
    },
    {
      "time": "09:31:36",
      "price": 11.61,
      "change": -0.01,
      "voturnover": 3,
      "vaturnover": 3483
    },
    {
      "time": "09:31:24",
      "price": 11.62,
      "change": 0,
      "voturnover": 1,
      "vaturnover": 1162
    },
    {
      "time": "09:31:21",
      "price": 11.62,
      "change": -0.03,
      "voturnover": 54,
      "vaturnover": 62748
    },
    {
      "time": "09:31:15",
      "price": 11.65,
      "change": 0,
      "voturnover": 0,
      "vaturnover": 0
    },
    {
      "time": "09:31:12",
      "price": 11.65,
      "change": 0,
      "voturnover": 1,
      "vaturnover": 1165
    },
    {
      "time": "09:31:09",
      "price": 11.65,
      "change": 0,
      "voturnover": 1,
      "vaturnover": 1165
    },
    {
      "time": "09:31:06",
      "price": 11.65,
      "change": 0,
      "voturnover": 1,
      "vaturnover": 1165
    },
    {
      "time": "09:30:57",
      "price": 11.65,
      "change": 0,
      "voturnover": 0,
      "vaturnover": 0
    },
    {
      "time": "09:30:48",
      "price": 11.65,
      "change": 0.01,
      "voturnover": 10,
      "vaturnover": 11650
    },
    {
      "time": "09:30:45",
      "price": 11.64,
      "change": 0.01,
      "voturnover": 1,
      "vaturnover": 1164
    },
    {
      "time": "09:30:42",
      "price": 11.63,
      "change": -0.02,
      "voturnover": 30,
      "vaturnover": 34890
    },
    {
      "time": "09:30:33",
      "price": 11.65,
      "change": -0.04,
      "voturnover": 64,
      "vaturnover": 74560
    },
    {
      "time": "09:30:21",
      "price": 11.69,
      "change": 0,
      "voturnover": 2,
      "vaturnover": 2338
    },
    {
      "time": "09:30:18",
      "price": 11.69,
      "change": -0.03,
      "voturnover": 4,
      "vaturnover": 4676
    },
    {
      "time": "09:30:15",
      "price": 11.72,
      "change": 0,
      "voturnover": 0,
      "vaturnover": 0
    },
    {
      "time": "09:30:12",
      "price": 11.72,
      "change": -0.01,
      "voturnover": 1,
      "vaturnover": 1172
    },
    {
      "time": "09:30:09",
      "price": 11.73,
      "change": 0,
      "voturnover": 5,
      "vaturnover": 5865
    },
    {
      "time": "09:30:06",
      "price": 11.73,
      "change": 0,
      "voturnover": 15,
      "vaturnover": 17595
    },
    {
      "time": "09:30:04",
      "price": 11.73,
      "change": 0,
      "voturnover": 38,
      "vaturnover": 44574
    },
    {
      "time": "09:30:00",
      "price": 11.73,
      "change": -0.03,
      "voturnover": 3,
      "vaturnover": 3519
    },
    {
      "time": "09:25:00",
      "price": 11.76,
      "change": 11.76,
      "voturnover": 46,
      "vaturnover": 54096
    }
  ]
}